prosac/__init__.py
prosac/random_consensus.py
prosac-0.0.1.dist-info/METADATA
prosac-0.0.1.dist-info/WHEEL
prosac-0.0.1.dist-info/licenses/LICENSE
prosac-0.0.1.dist-info/RECORD
