Metadata-Version: 2.3
Name: prosac
Version: 0.0.1
Summary: PROSAC algorithm in python
Project-URL: Homepage, https://github.com/willGuimont/prosac
Project-URL: Issues, https://github.com/willGuimont/prosac/issues
Author-email: William Guimont-Martin <william.guimont-martin@norlab.ulaval.ca>
License: MIT License
License-File: LICENSE
Classifier: License :: OSI Approved :: MIT License
Classifier: Operating System :: OS Independent
Classifier: Programming Language :: Python :: 3
Requires-Python: >=3.8
Requires-Dist: matplotlib
Requires-Dist: numpy
Requires-Dist: scipy
